{
  "Servers": {
    "1": {
      "Name": "yelli prod",
      "Group": "Spec-Driven",
      "Host": "yelli_prod_postgres",
      "Port": 5432,
      "MaintenanceDB": "yelli_prod",
      "Username": "yelli_prod",
      "SSLMode": "prefer",
      "PassFile": "/pgpassfile"
    },
    "2": {
      "Name": "yelli prod (via pgbouncer)",
      "Group": "Spec-Driven",
      "Host": "yelli_prod_pgbouncer",
      "Port": 5432,
      "MaintenanceDB": "yelli_prod",
      "Username": "yelli_prod",
      "SSLMode": "prefer",
      "PassFile": "/pgpassfile"
    }
  }
}
